pelican/plugins/granular_signals/__init__.py
pelican_granular_signals-1.2.0.dist-info/LICENSE.txt
pelican_granular_signals-1.2.0.dist-info/METADATA
pelican_granular_signals-1.2.0.dist-info/WHEEL
pelican_granular_signals-1.2.0.dist-info/RECORD
