Metadata-Version: 2.1
Name: pelican-granular-signals
Version: 1.2.0
Summary: Add more granular signals to Pelican.
License: MIT
Author: Kurt McKee
Author-email: contactme@kurtmckee.org
Requires-Python: >=3.9
Classifier: License :: OSI Approved :: MIT License
Classifier: Programming Language :: Python :: 3
Classifier: Programming Language :: Python :: 3.9
Classifier: Programming Language :: Python :: 3.10
Classifier: Programming Language :: Python :: 3.11
Classifier: Programming Language :: Python :: 3.12
